aiopixooapi/__init__.py
aiopixooapi/base.py
aiopixooapi/divoom.py
aiopixooapi/exceptions.py
aiopixooapi/pixoo64.py
aiopixooapi-0.2.2.dist-info/METADATA
aiopixooapi-0.2.2.dist-info/WHEEL
aiopixooapi-0.2.2.dist-info/licenses/LICENSE
aiopixooapi-0.2.2.dist-info/RECORD
