Metadata-Version: 2.4
Name: aiopixooapi
Version: 0.2.2
Summary: Asynchronous Python library for Divoom Pixoo64 LED display
Project-URL: Homepage, https://github.com/KoenDierckx/aiopixooapi
Project-URL: Documentation, https://github.com/KoenDierckx/aiopixooapi#readme
Project-URL: Repository, https://github.com/KoenDierckx/aiopixooapi.git
Project-URL: Issues, https://github.com/KoenDierckx/aiopixooapi/issues
Author-email: Koen Dierckx <koen.dierckx@gmail.com>
License-Expression: AGPL-3.0
License-File: LICENSE
Classifier: Development Status :: 3 - Alpha
Classifier: Intended Audience :: Developers
Classifier: License :: OSI Approved :: GNU Affero General Public License v3
Classifier: Programming Language :: Python :: 3
Requires-Python: >=3.8
Requires-Dist: aiohttp>=3.9.0
Requires-Dist: typing-extensions
Provides-Extra: test
Requires-Dist: aioresponses; extra == 'test'
Requires-Dist: flake8; extra == 'test'
Requires-Dist: pytest; extra == 'test'
Requires-Dist: pytest-asyncio; extra == 'test'
Requires-Dist: ruff; extra == 'test'
